ocht/__init__.py
ocht/cli.py
ocht/adapters/base.py
ocht/adapters/ollama.py
ocht/core/__init__.py
ocht/core/db.py
ocht/core/migration.py
ocht/core/models.py
ocht/core/version.py
ocht/repositories/__init__.py
ocht/repositories/llm_provider_config.py
ocht/repositories/message.py
ocht/repositories/model.py
ocht/repositories/prompt_template.py
ocht/repositories/setting.py
ocht/repositories/workspace.py
ocht/services/__init__.py
ocht/services/chat.py
ocht/services/config.py
ocht/services/model_manager.py
ocht/services/prompt_manager.py
ocht/services/provider_manager.py
ocht/services/workspace.py
ocht/tui/app.py
ocht/tui/screens/model_manager.py
ocht/tui/screens/model_selector.py
ocht/tui/screens/provider_manager.py
ocht/tui/screens/provider_selector.py
ocht/tui/widgets/chat_bubble.py
ocht-0.1.0.dist-info/licenses/LICENSE
ocht-0.1.0.dist-info/METADATA
ocht-0.1.0.dist-info/WHEEL
ocht-0.1.0.dist-info/entry_points.txt
ocht-0.1.0.dist-info/top_level.txt
ocht-0.1.0.dist-info/RECORD
