Metadata-Version: 2.4
Name: ocht
Version: 0.1.0
Summary: Modulare Python-TUI zur Steuerung von LLMs via LangChain
Author-email: Roman Thimian <roman.thimian@me.com>
License-Expression: MIT
Keywords: tui,langchain,llm,cli
Requires-Python: >=3.9
License-File: LICENSE
Requires-Dist: alembic>=1.15.2
Requires-Dist: click>=8.1.8
Requires-Dist: langchain>=0.3.26
Requires-Dist: langchain-ollama>=0.3.3
Requires-Dist: ollama>=0.4.8
Requires-Dist: rich>=14.0.0
Requires-Dist: sqlmodel>=0.0.24
Requires-Dist: textual>=3.2.0
Dynamic: license-file
